vimapi/__init__.py
vimapi/extended_vim.py
vimapi/mock_vim.py
vimapi/pyvimplugin.py
vimapi/vimapi.py
vimapi-0.0.1.dist-info/AUTHORS.md
vimapi-0.0.1.dist-info/LICENSE
vimapi-0.0.1.dist-info/METADATA
vimapi-0.0.1.dist-info/WHEEL
vimapi-0.0.1.dist-info/top_level.txt
vimapi-0.0.1.dist-info/RECORD
