Metadata-Version: 2.1
Name: vimapi
Version: 0.0.1
Summary: Vim API to control and configure the vim editor using python.
Home-page: https://github.com/julien-h/vimapi
Author: Julien Harbulot
Author-email: web@julienh.fr
License: MIT license
Keywords: vimapi vim plugin neovim api vim-api pyfile py3file pyvim vimpy
Platform: UNKNOWN
Classifier: Development Status :: 2 - Pre-Alpha
Classifier: Intended Audience :: Developers
Classifier: License :: OSI Approved :: MIT License
Classifier: Natural Language :: English
Classifier: Programming Language :: Python :: 2
Classifier: Programming Language :: Python :: 2.7
Classifier: Programming Language :: Python :: 3
Classifier: Programming Language :: Python :: 3.4
Classifier: Programming Language :: Python :: 3.5
Classifier: Programming Language :: Python :: 3.6
Classifier: Programming Language :: Python :: 3.7
